[{"id":1,"prefix":"OZ5","compound_name":"Semaglutide","nominal_dose":"5mg","created_at":"2026-04-27T22:07:44.954Z","updated_at":"2026-04-27T22:07:44.954Z"},{"id":2,"prefix":"OZ10","compound_name":"Semaglutide","nominal_dose":"10mg","created_at":"2026-04-27T22:07:44.954Z","updated_at":"2026-04-27T22:07:44.954Z"},{"id":3,"prefix":"OZ20","compound_name":"Semaglutide","nominal_dose":"20mg","created_at":"2026-04-27T22:07:44.954Z","updated_at":"2026-04-27T22:07:44.954Z"},{"id":4,"prefix":"ZE10","compound_name":"Tirzepatide","nominal_dose":"10mg","created_at":"2026-04-27T22:07:44.954Z","updated_at":"2026-04-27T22:07:44.954Z"},{"id":5,"prefix":"ZE15","compound_name":"Tirzepatide","nominal_dose":"15mg","created_at":"2026-04-27T22:07:44.954Z","updated_at":"2026-04-27T22:07:44.954Z"},{"id":6,"prefix":"ZE20","compound_name":"Tirzepatide","nominal_dose":"20mg","created_at":"2026-04-27T22:07:44.954Z","updated_at":"2026-04-27T22:07:44.954Z"},{"id":7,"prefix":"ZE30","compound_name":"Tirzepatide","nominal_dose":"30mg","created_at":"2026-04-27T22:07:44.954Z","updated_at":"2026-04-27T22:07:44.954Z"},{"id":8,"prefix":"ZE45","compound_name":"Tirzepatide","nominal_dose":"45mg","created_at":"2026-04-27T22:07:44.954Z","updated_at":"2026-04-27T22:07:44.954Z"},{"id":9,"prefix":"ZE60","compound_name":"Tirzepatide","nominal_dose":"60mg","created_at":"2026-04-27T22:07:44.954Z","updated_at":"2026-04-27T22:07:44.954Z"},{"id":10,"prefix":"ZE100","compound_name":"Tirzepatide","nominal_dose":"100mg","created_at":"2026-04-27T22:07:44.954Z","updated_at":"2026-04-27T22:07:44.954Z"},{"id":11,"prefix":"RE10","compound_name":"Retatrutide","nominal_dose":"10mg","created_at":"2026-04-27T22:07:44.954Z","updated_at":"2026-04-27T22:07:44.954Z"},{"id":12,"prefix":"RE20","compound_name":"Retatrutide","nominal_dose":"20mg","created_at":"2026-04-27T22:07:44.954Z","updated_at":"2026-04-27T22:07:44.954Z"},{"id":13,"prefix":"RE30","compound_name":"Retatrutide","nominal_dose":"30mg","created_at":"2026-04-27T22:07:44.954Z","updated_at":"2026-04-27T22:07:44.954Z"},{"id":14,"prefix":"RE40","compound_name":"Retatrutide","nominal_dose":"40mg","created_at":"2026-04-27T22:07:44.954Z","updated_at":"2026-04-27T22:07:44.954Z"},{"id":15,"prefix":"RE50","compound_name":"Retatrutide","nominal_dose":"50mg","created_at":"2026-04-27T22:07:44.954Z","updated_at":"2026-04-27T22:07:44.954Z"},{"id":16,"prefix":"RE60","compound_name":"Retatrutide","nominal_dose":"60mg","created_at":"2026-04-27T22:07:44.954Z","updated_at":"2026-04-27T22:07:44.954Z"},{"id":17,"prefix":"CAG5","compound_name":"Cagrilintide","nominal_dose":"5mg","created_at":"2026-04-27T22:07:44.954Z","updated_at":"2026-04-27T22:07:44.954Z"},{"id":18,"prefix":"CAG10","compound_name":"Cagrilintide","nominal_dose":"10mg","created_at":"2026-04-27T22:07:44.954Z","updated_at":"2026-04-27T22:07:44.954Z"},{"id":19,"prefix":"51Q50","compound_name":"5-Amino-1-methylquinolinium","nominal_dose":"50mg","created_at":"2026-04-27T22:07:44.954Z","updated_at":"2026-04-27T22:07:44.954Z"},{"id":20,"prefix":"51Q10","compound_name":"5-Amino-1-methylquinolinium","nominal_dose":"10mg","created_at":"2026-04-27T22:07:44.954Z","updated_at":"2026-04-27T22:07:44.954Z"},{"id":21,"prefix":"T/B55","compound_name":"BPC-157/TB-500","nominal_dose":"5/5mg","created_at":"2026-04-27T22:07:44.954Z","updated_at":"2026-04-27T22:07:44.954Z"},{"id":22,"prefix":"T/B1010","compound_name":"BPC-157/TB-500 (TB4)","nominal_dose":"10/10mg","created_at":"2026-04-27T22:07:44.954Z","updated_at":"2026-04-27T22:07:44.954Z"},{"id":23,"prefix":"BP10","compound_name":"BPC-157","nominal_dose":"10mg","created_at":"2026-04-27T22:07:44.954Z","updated_at":"2026-04-27T22:07:44.954Z"},{"id":24,"prefix":"BP20","compound_name":"BPC-157","nominal_dose":"20mg","created_at":"2026-04-27T22:07:44.954Z","updated_at":"2026-04-27T22:07:44.954Z"},{"id":25,"prefix":"TB10","compound_name":"TB-500","nominal_dose":"10mg","created_at":"2026-04-27T22:07:44.954Z","updated_at":"2026-04-27T22:07:44.954Z"},{"id":26,"prefix":"TB20","compound_name":"TB-500","nominal_dose":"20mg","created_at":"2026-04-27T22:07:44.954Z","updated_at":"2026-04-27T22:07:44.954Z"},{"id":27,"prefix":"TB410","compound_name":"TB-500 (TB4)","nominal_dose":"10mg","created_at":"2026-04-27T22:07:44.954Z","updated_at":"2026-04-27T22:07:44.954Z"},{"id":28,"prefix":"TBF10","compound_name":"TB-500 Fragment","nominal_dose":"10mg","created_at":"2026-04-27T22:07:44.954Z","updated_at":"2026-04-27T22:07:44.954Z"},{"id":29,"prefix":"HK100","compound_name":"GHK-Cu","nominal_dose":"100mg","created_at":"2026-04-27T22:07:44.954Z","updated_at":"2026-04-27T22:07:44.954Z"},{"id":30,"prefix":"HK50","compound_name":"GHK-Cu","nominal_dose":"50mg","created_at":"2026-04-27T22:07:44.954Z","updated_at":"2026-04-27T22:07:44.954Z"},{"id":31,"prefix":"HK/KP50/20","compound_name":"GHK-Cu2+/KPV","nominal_dose":"50/20mg","created_at":"2026-04-27T22:07:44.954Z","updated_at":"2026-04-27T22:07:44.954Z"},{"id":32,"prefix":"KP10","compound_name":"KPV","nominal_dose":"10mg","created_at":"2026-04-27T22:07:44.954Z","updated_at":"2026-04-27T22:07:44.954Z"},{"id":33,"prefix":"KP30","compound_name":"KPV","nominal_dose":"30mg","created_at":"2026-04-27T22:07:44.954Z","updated_at":"2026-04-27T22:07:44.954Z"},{"id":34,"prefix":"SS10","compound_name":"SS-31","nominal_dose":"10mg","created_at":"2026-04-27T22:07:44.954Z","updated_at":"2026-04-27T22:07:44.954Z"},{"id":35,"prefix":"SS30","compound_name":"SS-31","nominal_dose":"30mg","created_at":"2026-04-27T22:07:44.954Z","updated_at":"2026-04-27T22:07:44.954Z"},{"id":36,"prefix":"SS50","compound_name":"Elamipretide (SS-31)","nominal_dose":"50mg","created_at":"2026-04-27T22:07:44.954Z","updated_at":"2026-04-27T22:07:44.954Z"},{"id":37,"prefix":"MO10","compound_name":"MOTS-C","nominal_dose":"10mg","created_at":"2026-04-27T22:07:44.954Z","updated_at":"2026-04-27T22:07:44.954Z"},{"id":38,"prefix":"MO20","compound_name":"MOTS-C","nominal_dose":"20mg","created_at":"2026-04-27T22:07:44.954Z","updated_at":"2026-04-27T22:07:44.954Z"},{"id":39,"prefix":"M010","compound_name":"MOTS-C","nominal_dose":"10mg","created_at":"2026-04-27T22:07:44.954Z","updated_at":"2026-04-27T22:07:44.954Z"},{"id":40,"prefix":"M040","compound_name":"MOTS-C","nominal_dose":"40mg","created_at":"2026-04-27T22:07:44.954Z","updated_at":"2026-04-27T22:07:44.954Z"},{"id":41,"prefix":"PE10","compound_name":"PE-22-28","nominal_dose":"10mg","created_at":"2026-04-27T22:07:44.954Z","updated_at":"2026-04-27T22:07:44.954Z"},{"id":42,"prefix":"NASX10","compound_name":"N-Acetyl Semax","nominal_dose":"10mg","created_at":"2026-04-27T22:07:44.954Z","updated_at":"2026-04-27T22:07:44.954Z"},{"id":43,"prefix":"NASX50","compound_name":"N-Acetyl Semax","nominal_dose":"50mg","created_at":"2026-04-27T22:07:44.954Z","updated_at":"2026-04-27T22:07:44.954Z"},{"id":44,"prefix":"NASK10","compound_name":"N-Acetyl Selank Amidate","nominal_dose":"10mg","created_at":"2026-04-27T22:07:44.954Z","updated_at":"2026-04-27T22:07:44.954Z"},{"id":45,"prefix":"NASK50","compound_name":"N-Acetyl Selank","nominal_dose":"50mg","created_at":"2026-04-27T22:07:44.954Z","updated_at":"2026-04-27T22:07:44.954Z"},{"id":46,"prefix":"SK10","compound_name":"Selank","nominal_dose":"10mg","created_at":"2026-04-27T22:07:44.954Z","updated_at":"2026-04-27T22:07:44.954Z"},{"id":47,"prefix":"SX10","compound_name":"Semax","nominal_dose":"10mg","created_at":"2026-04-27T22:07:44.954Z","updated_at":"2026-04-27T22:07:44.954Z"},{"id":48,"prefix":"MT1","compound_name":"Melanotan I","nominal_dose":"10mg","created_at":"2026-04-27T22:07:44.954Z","updated_at":"2026-04-27T22:07:44.954Z"},{"id":49,"prefix":"MT2","compound_name":"Melanotan II","nominal_dose":"10mg","created_at":"2026-04-27T22:07:44.954Z","updated_at":"2026-04-27T22:07:44.954Z"},{"id":50,"prefix":"MT210","compound_name":"Melanotan 2","nominal_dose":"10mg","created_at":"2026-04-27T22:07:44.954Z","updated_at":"2026-04-27T22:07:44.954Z"},{"id":51,"prefix":"TA110","compound_name":"Thymosin Alpha-1","nominal_dose":"10mg","created_at":"2026-04-27T22:07:44.954Z","updated_at":"2026-04-27T22:07:44.954Z"},{"id":52,"prefix":"CJND","compound_name":"CJC no DAC/Ipamorelin","nominal_dose":"5/5mg","created_at":"2026-04-27T22:07:44.954Z","updated_at":"2026-04-27T22:07:44.954Z"},{"id":53,"prefix":"CI1010","compound_name":"CJC DAC/Ipamorelin","nominal_dose":"10/10mg","created_at":"2026-04-27T22:07:44.954Z","updated_at":"2026-04-27T22:07:44.954Z"},{"id":54,"prefix":"CJD5","compound_name":"CJC-1295 DAC","nominal_dose":"5mg","created_at":"2026-04-27T22:07:44.954Z","updated_at":"2026-04-27T22:07:44.954Z"},{"id":55,"prefix":"TE10","compound_name":"Tesamorelin","nominal_dose":"10mg","created_at":"2026-04-27T22:07:44.954Z","updated_at":"2026-04-27T22:07:44.954Z"},{"id":56,"prefix":"TE20","compound_name":"Tesamorelin","nominal_dose":"20mg","created_at":"2026-04-27T22:07:44.954Z","updated_at":"2026-04-27T22:07:44.954Z"},{"id":57,"prefix":"T/155","compound_name":"Tesamorelin/Ipamorelin","nominal_dose":"15/5mg","created_at":"2026-04-27T22:07:44.954Z","updated_at":"2026-04-27T22:07:44.954Z"},{"id":58,"prefix":"H10","compound_name":"Human Growth Hormone","nominal_dose":"10mg","created_at":"2026-04-27T22:07:44.954Z","updated_at":"2026-04-27T22:07:44.954Z"},{"id":59,"prefix":"PT10","compound_name":"PT-141","nominal_dose":"10mg","created_at":"2026-04-27T22:07:44.954Z","updated_at":"2026-04-27T22:07:44.954Z"},{"id":60,"prefix":"SN10","compound_name":"Snap-8","nominal_dose":"10mg","created_at":"2026-04-27T22:07:44.954Z","updated_at":"2026-04-27T22:07:44.954Z"},{"id":61,"prefix":"VIP","compound_name":"VIP","nominal_dose":"10mg","created_at":"2026-04-27T22:07:44.954Z","updated_at":"2026-04-27T22:07:44.954Z"},{"id":62,"prefix":"NA500","compound_name":"NAD+","nominal_dose":"500mg","created_at":"2026-04-27T22:07:44.954Z","updated_at":"2026-04-27T22:07:44.954Z"},{"id":63,"prefix":"FOX10","compound_name":"Fox-04","nominal_dose":"10mg","created_at":"2026-04-27T22:07:44.954Z","updated_at":"2026-04-27T22:07:44.954Z"},{"id":64,"prefix":"EP10","compound_name":"Epithalon","nominal_dose":"10mg","created_at":"2026-04-27T22:07:44.954Z","updated_at":"2026-04-27T22:07:44.954Z"},{"id":65,"prefix":"EP50","compound_name":"Epithalon","nominal_dose":"50mg","created_at":"2026-04-27T22:07:44.954Z","updated_at":"2026-04-27T22:07:44.954Z"},{"id":66,"prefix":"AR16","compound_name":"ARA-290","nominal_dose":"16mg","created_at":"2026-04-27T22:07:44.954Z","updated_at":"2026-04-27T22:07:44.954Z"},{"id":67,"prefix":"ARA16","compound_name":"ARA-290","nominal_dose":"16mg","created_at":"2026-04-27T22:07:44.954Z","updated_at":"2026-04-27T22:07:44.954Z"},{"id":68,"prefix":"DS5","compound_name":"DSIP","nominal_dose":"5mg","created_at":"2026-04-27T22:07:44.954Z","updated_at":"2026-04-27T22:07:44.954Z"},{"id":69,"prefix":"DS10","compound_name":"DSIP","nominal_dose":"10mg","created_at":"2026-04-27T22:07:44.954Z","updated_at":"2026-04-27T22:07:44.954Z"},{"id":70,"prefix":"IG1","compound_name":"IGF-1 LR3","nominal_dose":"1mg","created_at":"2026-04-27T22:07:44.954Z","updated_at":"2026-04-27T22:07:44.954Z"},{"id":71,"prefix":"G210","compound_name":"GHRP-2","nominal_dose":"10mg","created_at":"2026-04-27T22:07:44.954Z","updated_at":"2026-04-27T22:07:44.954Z"},{"id":72,"prefix":"G610","compound_name":"GHRP-6","nominal_dose":"10mg","created_at":"2026-04-27T22:07:44.954Z","updated_at":"2026-04-27T22:07:44.954Z"},{"id":73,"prefix":"A05","compound_name":"AOD-9604","nominal_dose":"5mg","created_at":"2026-04-27T22:07:44.954Z","updated_at":"2026-04-27T22:07:44.954Z"},{"id":74,"prefix":"IP10","compound_name":"Ipamorelin","nominal_dose":"10mg","created_at":"2026-04-27T22:07:44.954Z","updated_at":"2026-04-27T22:07:44.954Z"},{"id":75,"prefix":"SR5","compound_name":"Sermorelin","nominal_dose":"5mg","created_at":"2026-04-27T22:07:44.954Z","updated_at":"2026-04-27T22:07:44.954Z"},{"id":76,"prefix":"SUR10","compound_name":"Survotide","nominal_dose":"10mg","created_at":"2026-04-27T22:07:44.954Z","updated_at":"2026-04-27T22:07:44.954Z"},{"id":77,"prefix":"KL080","compound_name":"GHK-Cu/BPC-157/TB-500/KPV","nominal_dose":"80mg total","created_at":"2026-04-27T22:07:44.954Z","updated_at":"2026-04-27T22:07:44.954Z"},{"id":78,"prefix":"KLO80","compound_name":"KLOW blend","nominal_dose":"80mg","created_at":"2026-04-27T22:07:44.954Z","updated_at":"2026-04-27T22:07:44.954Z"},{"id":79,"prefix":"GLO80","compound_name":"GLOW blend","nominal_dose":"80mg","created_at":"2026-04-27T22:07:44.954Z","updated_at":"2026-04-27T22:07:44.954Z"},{"id":80,"prefix":"ILLUM","compound_name":"illumineeuro","nominal_dose":"","created_at":"2026-04-27T22:07:44.954Z","updated_at":"2026-04-27T22:07:44.954Z"}]